aiommost/__init__.py
aiommost/client.py
aiommost/errors.py
aiommost/py.typed
aiommost/schemas.py
aiommost/channels/__init__.py
aiommost/channels/client.py
aiommost/channels/schemas.py
aiommost/posts/__init__.py
aiommost/posts/client.py
aiommost/posts/schemas.py
aiommost/users/__init__.py
aiommost/users/client.py
aiommost/users/schemas.py
aiommost-0.3.0.dist-info/LICENSE
aiommost-0.3.0.dist-info/WHEEL
aiommost-0.3.0.dist-info/METADATA
aiommost-0.3.0.dist-info/RECORD
